xcd/__init__.py
xcd/assets/fonts/calibri.ttf
xcd/assets/fonts/calibrib.ttf
xcd/assets/fonts/calibrii.ttf
xcd/assets/fonts/calibril.ttf
xcd/assets/fonts/calibrili.ttf
xcd/core/XCD_data.py
xcd/core/XCD_db.py
xcd/core/XCD_kits.py
xcd/core/XCD_parsing.py
xcd/core/XCD_report.py
xcd/core/XCD_utils.py
xcd/core/__init__.py
xcd/django/__init__.py
xcd/django/admin.py
xcd/django/apps.py
xcd/django/forms.py
xcd/django/manage.py
xcd/django/models.py
xcd/django/tests.py
xcd/django/urls.py
xcd/django/views.py
xcd/django/migrations/0001_initial.py
xcd/django/migrations/0002_alter_quantification_options_alter_sample_options.py
xcd/django/migrations/0003_alter_quantification_table_alter_sample_table.py
xcd/django/migrations/__init__.py
xcd/django/static/XCD2_bg.jpg
xcd/django/static/xcd/css/style.css
xcd/django/templates/xcd/index.html
xcd/django/xcdweb/__init__.py
xcd/django/xcdweb/asgi.py
xcd/django/xcdweb/settings.py
xcd/django/xcdweb/urls.py
xcd/django/xcdweb/wsgi.py
xcd/gui/XCD.py
xcd/gui/XCD_gui.py
xcd/streamlit/app.py
xcd/streamlit/cli.py
xcd-2.0.11.dist-info/METADATA
xcd-2.0.11.dist-info/WHEEL
xcd-2.0.11.dist-info/entry_points.txt
xcd-2.0.11.dist-info/top_level.txt
xcd-2.0.11.dist-info/RECORD
