Metadata-Version: 2.4
Name: xcd
Version: 2.0.11
Summary: X-CELL DNA
Author: Michal Mantič
License: MIT
Requires-Python: >=3.10
Requires-Dist: pandas
Requires-Dist: reportlab
Provides-Extra: django
Requires-Dist: Django>=4.2; extra == "django"
Requires-Dist: psycopg2-binary; extra == "django"
Provides-Extra: streamlit
Requires-Dist: streamlit>=1.36; extra == "streamlit"
